labhub/__init__.py
labhub/src/__init__.py
labhub/src/files.py
labhub/src/loader.py
labhub/src/repos/__init__.py
labhub/src/repos/base_repo.py
labhub/src/repos/github.py
labhub/src/repos/gitlab.py
labhub-1.2.0.dist-info/METADATA
labhub-1.2.0.dist-info/WHEEL
labhub-1.2.0.dist-info/licenses/LICENSE
labhub-1.2.0.dist-info/RECORD
