Metadata-Version: 2.3
Name: labhub
Version: 1.2.0
Summary: Seamlessly work with with Github, Gitlab and self-hosted Gitlab repositories using one interface
Project-URL: Homepage, https://github.com/hamolicious/labhub
Project-URL: Issues, https://github.com/hamolicious/labhub/issues
Author-email: hamolicious <hamolicious@hamolicious.net>
Classifier: License :: OSI Approved :: MIT License
Classifier: Operating System :: OS Independent
Classifier: Programming Language :: Python :: 3
Requires-Python: >=3.12
Requires-Dist: pygithub==2.4.0
Requires-Dist: python-gitlab==4.12.2
